whoisdomain/__init__.py
whoisdomain/doWhoisCommand.py
whoisdomain/domain.py
whoisdomain/exceptions.py
whoisdomain/handleDateStrings.py
whoisdomain/helpers.py
whoisdomain/lastWhois.py
whoisdomain/main.py
whoisdomain/procFunc.py
whoisdomain/processWhoisDomainRequest.py
whoisdomain/tldInfo.py
whoisdomain/version.py
whoisdomain/whoisCliInterface.py
whoisdomain/whoisParser.py
whoisdomain/cache/__init__.py
whoisdomain/cache/dbmCache.py
whoisdomain/cache/dummyCache.py
whoisdomain/cache/redisCache.py
whoisdomain/cache/simpleCacheBase.py
whoisdomain/cache/simpleCacheWithFile.py
whoisdomain/context/__init__.py
whoisdomain/context/dataContext.py
whoisdomain/context/parameterContext.py
whoisdomain/strings/__init__.py
whoisdomain/strings/ignoreStrings.py
whoisdomain/strings/noneStrings.py
whoisdomain/strings/quotaStrings.py
whoisdomain/tldDb/__init__.py
whoisdomain/tldDb/finders.py
whoisdomain/tldDb/groupers.py
whoisdomain/tldDb/tld_regexpr.py
whoisdomain-1.20260106.1.dist-info/METADATA
whoisdomain-1.20260106.1.dist-info/WHEEL
whoisdomain-1.20260106.1.dist-info/entry_points.txt
whoisdomain-1.20260106.1.dist-info/licenses/LICENSE
whoisdomain-1.20260106.1.dist-info/RECORD
