Metadata-Version: 2.4
Name: whoisdomain
Version: 1.20260106.1
Summary: Python package for retrieving WHOIS information of domains.
Project-URL: Bug Tracker, https://github.com/mboot-github/WhoisDomain/issues
Project-URL: Home Page, https://github.com/mboot-github/WhoisDomain/
Project-URL: Repository, https://github.com/mboot-github/WhoisDomain/
Author: mboot-github
Maintainer-email: Maarten Boot <130295084+mboot-github@users.noreply.github.com>
License-Expression: MIT
License-File: LICENSE
Keywords: Python,domain,expiration,registrar,tld,whois
Classifier: Environment :: Console
Classifier: Intended Audience :: Developers
Classifier: License :: OSI Approved :: MIT License
Classifier: Operating System :: OS Independent
Classifier: Programming Language :: Python :: 3
Classifier: Topic :: Internet
Classifier: Topic :: Software Development :: Libraries :: Python Modules
Requires-Python: >3.6
